README.md
setup.py
pyicub/__init__.py
pyicub/config.py
pyicub/iCubHelper.py
pyicub/utils.py
pyicub.egg-info/PKG-INFO
pyicub.egg-info/SOURCES.txt
pyicub.egg-info/dependency_links.txt
pyicub.egg-info/not-zip-safe
pyicub.egg-info/top_level.txt
pyicub/controllers/GazeController.py
pyicub/controllers/PositionController.py
pyicub/controllers/__init__.py
pyicub/core/BufferedPort.py
pyicub/core/Logger.py
pyicub/core/Rpc.py
pyicub/core/__init__.py
pyicub/modules/__init__.py
pyicub/modules/emotions.py
pyicub/modules/face.py
pyicub/modules/faceLandmarks.py
pyicub/modules/speech.py